pharmbio/__init__.py
pharmbio/config.py
pharmbio/dataset.py
pharmbio/logger.py
pharmbio/qc.py
pharmbio/utils.py
pharmbio/vs.py
pharmbio/data_processing/__init__.py
pharmbio/data_processing/feature_aggregation.py
pharmbio/data_processing/quality_control.py
pharmbio/database/__init__.py
pharmbio/database/queries.py
pharmbio/dataset/__init__.py
pharmbio/dataset/cell_morphology.py
pharmbio/dataset/experiment.py
pharmbio/dataset/image_quality.py
pharmbio/visualization/__init__.py
pharmbio/visualization/plots.py
pharmbio-0.1.7.dist-info/LICENSE
pharmbio-0.1.7.dist-info/METADATA
pharmbio-0.1.7.dist-info/WHEEL
pharmbio-0.1.7.dist-info/top_level.txt
pharmbio-0.1.7.dist-info/RECORD
